linuxboost/__init__.py
linuxboost/apps.json
linuxboost/commands.json
linuxboost/installer.py
linuxboost/main.py
linuxboost/ui_main.py
linuxboost-0.1.2.dist-info/licenses/LICENSE
linuxboost-0.1.2.dist-info/METADATA
linuxboost-0.1.2.dist-info/WHEEL
linuxboost-0.1.2.dist-info/entry_points.txt
linuxboost-0.1.2.dist-info/top_level.txt
linuxboost-0.1.2.dist-info/RECORD
