Metadata-Version: 2.4
Name: linuxboost
Version: 0.1.2
Summary: A GUI app to quickly install Linux apps and commands
Author-email: Priyanshu Raj <prmahatha@gmail.com>
License: MIT
Requires-Python: >=3.7
License-File: LICENSE
Requires-Dist: PyQt5
Dynamic: license-file
